{
  "320829485009000022": {
    "status": "False Positive",
    "note": "Owner's parent lives in this house."
  },
  "320829496022000022": {
    "status": "Confirmed Rental",
    "note": "Confirmed rental from HomeownerReport 3-23-2026."
  },
  "320829484009000022": {
    "status": "Confirmed Rental",
    "note": "Confirmed rental from HomeownerReport 3-23-2026."
  },
  "320829478003000022": {
    "status": "Confirmed Rental",
    "note": "Confirmed rental from HomeownerReport 3-23-2026."
  },
  "320829376016000022": {
    "status": "Confirmed Rental",
    "note": "Confirmed rental from HomeownerReport 3-23-2026."
  },
  "320829376031000022": {
    "status": "Confirmed Rental",
    "note": "Confirmed rental from HomeownerReport 3-23-2026."
  },
  "320829484015000022": {
    "status": "Confirmed Rental",
    "note": "Confirmed rental from HomeownerReport 3-23-2026."
  },
  "320829379010000022": {
    "status": "Confirmed Rental",
    "note": "Confirmed rental from HomeownerReport 3-23-2026."
  },
  "320829496021000022": {
    "status": "Confirmed Rental",
    "note": "Confirmed rental from HomeownerReport 3-23-2026."
  },
  "320829496009000022": {
    "status": "Confirmed Rental",
    "note": "Confirmed rental from HomeownerReport 3-23-2026."
  },
  "320829434004000022": {
    "status": "Confirmed Rental",
    "note": "Confirmed rental from HomeownerReport 3-23-2026."
  },
  "320829463008000022": {
    "status": "Confirmed Rental",
    "note": "Confirmed rental from HomeownerReport 3-23-2026."
  },
  "320829479023000022": {
    "status": "Confirmed Rental",
    "note": "Confirmed rental from HomeownerReport 3-23-2026."
  },
  "320829485013000022": {
    "status": "Confirmed Rental",
    "note": "Confirmed rental from HomeownerReport 3-23-2026."
  },
  "320829485014000022": {
    "status": "Confirmed Rental",
    "note": "Confirmed rental from HomeownerReport 3-23-2026."
  },
  "320829379007000022": {
    "status": "Confirmed Rental",
    "note": "Confirmed rental from HomeownerReport 3-23-2026."
  },
  "320829379015000022": {
    "status": "Confirmed Rental",
    "note": "Confirmed rental from HomeownerReport 3-23-2026."
  },
  "320829485016000022": {
    "status": "Confirmed Rental",
    "note": "Confirmed rental from HomeownerReport 3-23-2026."
  },
  "320829485007000022": {
    "status": "Confirmed Rental",
    "note": "Confirmed rental from HomeownerReport 3-23-2026."
  },
  "320829492013000022": {
    "status": "Confirmed Rental",
    "note": "Confirmed rental from HomeownerReport 3-23-2026."
  },
  "320829492018000022": {
    "status": "Confirmed Rental",
    "note": "Confirmed rental from HomeownerReport 3-23-2026."
  },
  "320829494004000022": {
    "status": "Confirmed Rental",
    "note": "Confirmed rental from HomeownerReport 3-23-2026."
  },
  "320829495009000022": {
    "status": "Confirmed Rental",
    "note": "Confirmed rental from HomeownerReport 3-23-2026."
  },
  "320829382013000022": {
    "status": "Confirmed Rental",
    "note": "Confirmed rental from HomeownerReport 3-23-2026."
  },
  "320829382014000022": {
    "status": "Confirmed Rental",
    "note": "Confirmed rental from HomeownerReport 3-23-2026."
  },
  "320829495012000022": {
    "status": "Confirmed Rental",
    "note": "Confirmed rental from HomeownerReport 3-23-2026."
  },
  "320829495002000022": {
    "status": "Confirmed Rental",
    "note": "Confirmed rental from HomeownerReport 3-23-2026."
  },
  "320829462007000022": {
    "status": "Confirmed Rental",
    "note": "Confirmed rental from HomeownerReport 3-23-2026."
  },
  "320829480002000022": {
    "status": "Confirmed Rental",
    "note": "Confirmed rental from HomeownerReport 3-23-2026."
  },
  "320829479020000022": {
    "status": "Confirmed Rental",
    "note": "Confirmed rental from HomeownerReport 3-23-2026."
  },
  "320829485004000022": {
    "status": "Confirmed Rental",
    "note": "Confirmed rental from HomeownerReport 3-23-2026."
  },
  "320829483006000022": {
    "status": "Confirmed Rental",
    "note": "Confirmed rental from HomeownerReport 3-23-2026."
  },
  "320829376030000022": {
    "status": "Confirmed Rental",
    "note": "Confirmed rental from HomeownerReport 3-23-2026."
  },
  "320829478009000022": {
    "status": "Confirmed Rental",
    "note": "Confirmed rental from HomeownerReport 3-23-2026."
  },
  "320829391005000022": {
    "status": "Confirmed Rental",
    "note": "Confirmed rental from HomeownerReport 3-23-2026."
  },
  "320829378010000022": {
    "status": "Confirmed Rental",
    "note": "Confirmed rental from HomeownerReport 3-23-2026."
  },
  "320829479008000022": {
    "status": "Confirmed Rental",
    "note": "Confirmed rental from HomeownerReport 3-23-2026."
  },
  "320829476003000022": {
    "status": "Confirmed Rental",
    "note": "Confirmed rental from HomeownerReport 3-23-2026."
  },
  "320829436011000022": {
    "status": "Confirmed Rental",
    "note": "Confirmed rental from HomeownerReport 3-23-2026."
  },
  "320829460005000022": {
    "status": "Confirmed Rental",
    "note": "Confirmed rental from HomeownerReport 3-23-2026."
  },
  "320829377010000022": {
    "status": "Confirmed Rental",
    "note": "Confirmed rental from HomeownerReport 3-23-2026."
  },
  "320829376039000022": {
    "status": "Confirmed Rental",
    "note": "Confirmed rental from HomeownerReport 3-23-2026."
  },
  "320829485017000022": {
    "status": "Confirmed Rental",
    "note": "Confirmed rental from HomeownerReport 3-23-2026."
  },
  "320829479006000022": {
    "status": "Confirmed Rental",
    "note": "Confirmed rental from HomeownerReport 3-23-2026."
  },
  "320829376012000022": {
    "status": "Confirmed Rental",
    "note": "Confirmed rental from HomeownerReport 3-23-2026."
  },
  "320829482004000022": {
    "status": "Confirmed Rental",
    "note": "Confirmed rental from HomeownerReport 3-23-2026."
  },
  "320829376007000022": {
    "status": "Confirmed Rental",
    "note": "Confirmed rental from HomeownerReport 3-23-2026."
  },
  "320829492016000022": {
    "status": "Confirmed Rental",
    "note": "Confirmed rental from HomeownerReport 3-23-2026."
  },
  "320829378005000022": {
    "status": "Confirmed Rental",
    "note": "Confirmed rental from HomeownerReport 3-23-2026."
  },
  "320829485003000022": {
    "status": "Confirmed Rental",
    "note": "Confirmed rental from HomeownerReport 3-23-2026."
  },
  "320829381014000022": {
    "status": "Confirmed Rental",
    "note": "Confirmed rental from HomeownerReport 3-23-2026."
  },
  "320829495023000022": {
    "status": "Confirmed Rental",
    "note": "Confirmed rental from HomeownerReport 3-23-2026."
  },
  "320829382010000022": {
    "status": "Confirmed Rental",
    "note": "Confirmed rental from HomeownerReport 3-23-2026."
  },
  "320829495015000022": {
    "status": "Confirmed Rental",
    "note": "Confirmed rental from HomeownerReport 3-23-2026."
  },
  "320829495003000022": {
    "status": "Confirmed Rental",
    "note": "Confirmed rental from HomeownerReport 3-23-2026."
  },
  "320829376026000022": {
    "status": "Confirmed Rental",
    "note": "Confirmed rental from HomeownerReport 3-23-2026."
  },
  "320829492012000022": {
    "status": "Confirmed Rental",
    "note": "Confirmed rental from HomeownerReport 3-23-2026."
  },
  "320829483004000022": {
    "status": "Confirmed Rental",
    "note": "Confirmed rental from HomeownerReport 3-23-2026."
  },
  "320829379004000022": {
    "status": "Confirmed Rental",
    "note": "Confirmed rental from HomeownerReport 3-23-2026."
  },
  "320829381012000022": {
    "status": "Confirmed Rental",
    "note": "Confirmed rental from HomeownerReport 3-23-2026."
  },
  "320829494018000022": {
    "status": "Confirmed Rental",
    "note": "Confirmed rental from HomeownerReport 3-23-2026."
  },
  "320829483010000022": {
    "status": "Confirmed Rental",
    "note": "Confirmed rental from HomeownerReport 3-23-2026."
  },
  "320829380010000022": {
    "status": "Confirmed Rental",
    "note": "Confirmed rental from HomeownerReport 3-23-2026."
  },
  "320829493007000022": {
    "status": "Confirmed Rental",
    "note": "Confirmed rental from HomeownerReport 3-23-2026."
  },
  "320829379006000022": {
    "status": "Confirmed Rental",
    "note": "Confirmed rental from HomeownerReport 3-23-2026."
  },
  "320829376028000022": {
    "status": "Confirmed Rental",
    "note": "Confirmed rental from HomeownerReport 3-23-2026."
  },
  "320829476002000022": {
    "status": "Confirmed Rental",
    "note": "Confirmed rental from HomeownerReport 3-23-2026."
  },
  "320829376015000022": {
    "status": "Confirmed Rental",
    "note": "Confirmed rental from HomeownerReport 3-23-2026."
  },
  "320829493020000022": {
    "status": "Confirmed Rental",
    "note": "Confirmed rental from HomeownerReport 3-23-2026."
  },
  "320829480007000022": {
    "status": "Confirmed Rental",
    "note": "Confirmed rental from HomeownerReport 3-23-2026."
  },
  "320829464002000022": {
    "status": "Confirmed Rental",
    "note": "Confirmed rental from HomeownerReport 3-23-2026."
  },
  "320829493003000022": {
    "status": "Confirmed Rental",
    "note": "Confirmed rental from HomeownerReport 3-23-2026."
  },
  "320829463004000022": {
    "status": "Confirmed Rental",
    "note": "Confirmed rental from HomeownerReport 3-23-2026."
  },
  "320829479025000022": {
    "status": "Confirmed Rental",
    "note": "Confirmed rental from HomeownerReport 3-23-2026."
  },
  "320829380015000022": {
    "status": "Confirmed Rental",
    "note": "Confirmed rental from HomeownerReport 3-23-2026."
  },
  "320829486006000022": {
    "status": "Confirmed Rental",
    "note": "Confirmed rental from HomeownerReport 3-23-2026."
  },
  "320829428011000022": {
    "status": "Confirmed Rental",
    "note": "Confirmed rental from HomeownerReport 3-23-2026."
  }
}
